adcpipeline/__init__.py
adcpipeline/pipeline.py
adcpipeline-0.2.1.dist-info/LICENSE
adcpipeline-0.2.1.dist-info/METADATA
adcpipeline-0.2.1.dist-info/WHEEL
adcpipeline-0.2.1.dist-info/top_level.txt
adcpipeline-0.2.1.dist-info/RECORD
