Metadata-Version: 2.1
Name: adcpipeline
Version: 0.2.1
Summary: A pipeline for a structured way of working
Home-page: https://github.com/Amsterdam-Data-Collective/data-pipeline/tree/master
Author: Amsterdam Data Collective
Author-email: development@amsterdamdatacollective.com
Keywords: Data Science,Data Engineering,Data,Pipeline
Classifier: Intended Audience :: Developers
Classifier: Topic :: Software Development :: Build Tools
Classifier: Topic :: Scientific/Engineering :: Artificial Intelligence
Classifier: Topic :: Database
Classifier: Programming Language :: Python :: 3
Classifier: License :: OSI Approved :: MIT License
Classifier: Operating System :: OS Independent
Requires-Python: >=3.6
License-File: LICENSE
Requires-Dist: pandas
Requires-Dist: pyyaml
